zest/zodbupdate/__init__.py
zest/zodbupdate/renames.py
zest_zodbupdate-2.0.0.dist-info/METADATA
zest_zodbupdate-2.0.0.dist-info/WHEEL
zest_zodbupdate-2.0.0.dist-info/entry_points.txt
zest_zodbupdate-2.0.0.dist-info/top_level.txt
zest_zodbupdate-2.0.0.dist-info/RECORD
