Metadata-Version: 2.4
Name: zest.zodbupdate
Version: 2.0.0
Summary: zodbupdate rename rules by Zest
Home-page: https://github.com/zestsoftware/zest.zodbupdate
Author: Maurits van Rees
Author-email: m.van.rees@zestsoftware.nl
License: ZPL-2.1
Keywords: Zope,Plone,ZODB
Classifier: Development Status :: 5 - Production/Stable
Classifier: Environment :: Web Environment
Classifier: Framework :: Plone
Classifier: Framework :: Plone :: 6.0
Classifier: Framework :: Plone :: 6.1
Classifier: Framework :: Plone :: 6.2
Classifier: Programming Language :: Python
Classifier: Programming Language :: Python :: 3.9
Classifier: Programming Language :: Python :: 3.10
Classifier: Programming Language :: Python :: 3.11
Classifier: Programming Language :: Python :: 3.12
Classifier: Programming Language :: Python :: 3.13
Classifier: Operating System :: OS Independent
Requires-Python: >=3.9
Requires-Dist: zodbupdate
